setup.py
obisidian_to_testlink/__init__.py
obisidian_to_testlink/libmarkdown.py
obisidian_to_testlink/libtestlinkxml.py
obisidian_to_testlink/main.py
obisidian_to_testlink.egg-info/PKG-INFO
obisidian_to_testlink.egg-info/SOURCES.txt
obisidian_to_testlink.egg-info/dependency_links.txt
obisidian_to_testlink.egg-info/entry_points.txt
obisidian_to_testlink.egg-info/top_level.txt