Metadata-Version: 1.0
Name: obisidian-to-testlink
Version: 1.2.2
Summary: Convert obisidian to TestLink xml
Home-page: UNKNOWN
Author: zhaobk
Author-email: zhaobk@nationalchip.com
License: UNKNOWN
Keywords: obisidian testlink testcase requirement
Platform: UNKNOWN
